{
   "formatVersion": 1,

   "name": "Optifine",
   "uid": "optifine.OptiFine",
   "version": "1.8.9_HD_U_H8",
   "releaseTime": "",
   "type": "release",

   "requires": [
      {
         "uid":"net.minecraft",
         "equals":"1.8.9"
      }
   ],

   "mainClass":"net.minecraft.launchwrapper.Launch",
   "+libraries": [
      { "name":"net.minecraft:launchwrapper:1.12" },
      {
         "downloads": {
            "artifact": {
                "sha1": "4b73738913453bcbca969d3e77f05ae0cf5b8a7e",
                "size": 1814543,
                "url": "https://www.dropbox.com/s/4qsgtiip658zq1b/OptiFine_1.8.9_HD_U_H8.jar?dl=1"
            }
         },
         "name":"optifine:OptiFine:1.8.9_HD_U_H8"
      }
   ],
   "+tweakers":[
      "optifine.OptiFineTweaker"
   ]
}