{
   "formatVersion": 1,

   "name": "Optifine",
   "uid": "optifine.OptiFine",
   "version": "1.7.2_HD_U_E7",
   "releaseTime": "2017-03-16",
   "type": "release",

   "requires": [
      {
         "uid":"net.minecraft",
         "equals":"1.7.2"
      }
   ],

   "mainClass":"net.minecraft.launchwrapper.Launch",
   "+libraries": [
      { "name":"net.minecraft:launchwrapper:1.12" },
      {
         "downloads": {
            "artifact": {
                "sha1": "99f20d449912cd860b409e4679c54dd8da43d55e",
                "size": 1611845,
                "url": "https://www.dropbox.com/s/d40ifk8w2jglspy/OptiFine_1.7.2_HD_U_E7.jar?dl=1"
            }
         },
         "name":"optifine:OptiFine:1.7.2_HD_U_E7"
      }
   ],
   "+tweakers":[
      "optifine.OptiFineTweaker"
   ]
}